drdmannturb/__init__.py
drdmannturb/common.py
drdmannturb/enums.py
drdmannturb/interpolation.py
drdmannturb/nn_modules.py
drdmannturb/parameters.py
drdmannturb/fluctuation_generation/__init__.py
drdmannturb/fluctuation_generation/cmap_util.py
drdmannturb/fluctuation_generation/covariance_kernels.py
drdmannturb/fluctuation_generation/fluctuation_field_generator.py
drdmannturb/fluctuation_generation/gaussian_random_fields.py
drdmannturb/fluctuation_generation/nn_covariance.py
drdmannturb/fluctuation_generation/sampling_methods.py
drdmannturb/fluctuation_generation/wind_plot.py
drdmannturb/spectra_fitting/__init__.py
drdmannturb/spectra_fitting/calibration.py
drdmannturb/spectra_fitting/data_generator.py
drdmannturb/spectra_fitting/loss_functions.py
drdmannturb/spectra_fitting/one_point_spectra.py
drdmannturb/spectra_fitting/power_spectra_rdt.py
drdmannturb-1.0.3.dist-info/LICENSE
drdmannturb-1.0.3.dist-info/METADATA
drdmannturb-1.0.3.dist-info/WHEEL
drdmannturb-1.0.3.dist-info/top_level.txt
drdmannturb-1.0.3.dist-info/RECORD
