Metadata-Version: 2.1
Name: drdmannturb
Version: 1.0.3
Summary: Mann turbulence modelling
Home-page: https://github.com/METHODS-Group/DRDMannTurb
Author: Alexey Izmailov, Matthew Meeker, Yorgos Deskos based on code by Brendan Keith et al.
Author-email: alizma@brown.edu, meeker.matthew@pm.me
License: BSD 2-clause
Classifier: Development Status :: 1 - Planning
Classifier: Intended Audience :: Science/Research
Classifier: License :: OSI Approved :: BSD License
Classifier: Operating System :: POSIX :: Linux
Classifier: Programming Language :: Python :: 3.9
License-File: LICENSE
Requires-Dist: torch
Requires-Dist: numpy (<2.0)
Requires-Dist: tqdm
Requires-Dist: scipy
Requires-Dist: matplotlib
Requires-Dist: pyevtk
Requires-Dist: pyfftw
Requires-Dist: tensorboard
